{
    "partners" : [
      [
        {
        "title": "UX Fellows",
        "source": "UXFellows_Logo",
        "link": "http://www.uxfellows.com/",
        "width": "120",
        "height": "34"
        }, 
        {
        "title": "International Usability & UX Qualification Board",
        "source": "UXQB_Logo",
        "link": "http://uxqb.org/en/training/recognized-training-providers/",
        "width": "120",
        "height": "49"
        }, 
        {
        "title": "Swiss Label",
        "source": "SwissLabel_Logo",
        "link": "http://www.swisslabel.ch/",
        "width": "64",
        "height": "70"
        },
        {
        "title": "Swiss ICT",
        "source": "SwissICT_Logo",
        "link": "http://www.swissict.ch/expertenwissen/fachgruppen/user-experience/",
        "width": "130",
        "height": "54"
        }
      ]
  ]  
}